financial/__init__.py
financial/server.py
financial_datasets_mcp_server-0.1.0.dist-info/licenses/LICENSE
financial_datasets_mcp_server-0.1.0.dist-info/METADATA
financial_datasets_mcp_server-0.1.0.dist-info/WHEEL
financial_datasets_mcp_server-0.1.0.dist-info/entry_points.txt
financial_datasets_mcp_server-0.1.0.dist-info/top_level.txt
financial_datasets_mcp_server-0.1.0.dist-info/RECORD
