Metadata-Version: 2.4
Name: financial-datasets-mcp-server
Version: 0.1.0
Summary: Add your description here
Requires-Python: >=3.13
License-File: LICENSE
Requires-Dist: httpx>=0.28.1
Requires-Dist: logging>=0.4.9.6
Requires-Dist: mcp[cli]>=1.6.0
Dynamic: license-file
